loggingx/__init__.py
loggingx/handlers.py
loggingx-1.0.1.dist-info/LICENSE
loggingx-1.0.1.dist-info/METADATA
loggingx-1.0.1.dist-info/WHEEL
loggingx-1.0.1.dist-info/top_level.txt
loggingx-1.0.1.dist-info/RECORD
