Metadata-Version: 2.1
Name: loggingx
Version: 1.0.1
Summary: logging拓展功能模块
Author-email: xingweidong <614968414@qq.com>
Maintainer-email: xingweidong <614968414@qq.com>
Project-URL: Homepage, https://github.com/Xingwd/loggingx
Project-URL: Issue Tracker, https://github.com/Xingwd/loggingx/issues
Project-URL: Code, https://github.com/Xingwd/loggingx
Project-URL: Releases, https://github.com/Xingwd/loggingx/releases
Classifier: Programming Language :: Python :: 3
Classifier: License :: OSI Approved :: MIT License
Classifier: Operating System :: OS Independent
Requires-Python: >=3.7
License-File: LICENSE
Provides-Extra: queue
Requires-Dist: redis (>=4.5.5) ; extra == 'queue'
